docs/conf.py
edpop_explorer/M21_fields.csv
edpop_explorer/__init__.py
edpop_explorer/__main__.py
edpop_explorer/cerl.py
edpop_explorer/edpopxshell.py
edpop_explorer/fields.py
edpop_explorer/marc21.py
edpop_explorer/normalizers.py
edpop_explorer/rdf.py
edpop_explorer/reader.py
edpop_explorer/record.py
edpop_explorer/sparqlreader.py
edpop_explorer/sql.py
edpop_explorer/srumarc21reader.py
edpop_explorer/srureader.py
edpop_explorer/external_data/__init__.py
edpop_explorer/external_data/deutsche_isil_agentur.py
edpop_explorer/normalization/relators.py
edpop_explorer/readers/__init__.py
edpop_explorer/readers/bibliopolis.py
edpop_explorer/readers/bnf.py
edpop_explorer/readers/cerl_thesaurus.py
edpop_explorer/readers/dutch_almanacs.py
edpop_explorer/readers/estc.py
edpop_explorer/readers/fbtee.py
edpop_explorer/readers/gallica.py
edpop_explorer/readers/hpb.py
edpop_explorer/readers/kb.py
edpop_explorer/readers/kvcs.py
edpop_explorer/readers/pierre_belle.py
edpop_explorer/readers/sbti.py
edpop_explorer/readers/stcn.py
edpop_explorer/readers/ustc.py
edpop_explorer/readers/utils.py
edpop_explorer/readers/vd.py
edpop_explorer-0.15.1.dist-info/licenses/LICENSE
tests/__init__.py
tests/conftest.py
tests/test_allreaders.py
tests/test_field.py
tests/test_reader.py
tests/test_record.py
tests/test_srureader.py
tests/external_data/__init__.py
tests/external_data/test_deutsche_isil_agentur.py
tests/readers/__init__.py
tests/readers/test_estc.py
tests/readers/test_kb.py
tests/readers/test_stcn.py
edpop_explorer-0.15.1.dist-info/METADATA
edpop_explorer-0.15.1.dist-info/WHEEL
edpop_explorer-0.15.1.dist-info/entry_points.txt
edpop_explorer-0.15.1.dist-info/top_level.txt
edpop_explorer-0.15.1.dist-info/RECORD
