Metadata-Version: 2.4
Name: edpop-explorer
Version: 0.15.1
Summary: Common interface to multiple library catalogues and bibliographical databases
Author-email: "Utrecht University, Centre for Digital Humanities - Research Software Lab" <cdh@uu.nl>
Project-URL: Homepage, https://github.com/UUDigitalHumanitieslab/edpop-explorer
Classifier: Development Status :: 2 - Pre-Alpha
Classifier: Environment :: Console
Classifier: Intended Audience :: Science/Research
Classifier: License :: OSI Approved :: BSD License
Classifier: Operating System :: OS Independent
Classifier: Programming Language :: Python :: 3
Requires-Python: >=3.9
License-File: LICENSE
Requires-Dist: sruthi<3,>=2.0.0
Requires-Dist: termcolor
Requires-Dist: appdirs
Requires-Dist: SPARQLWrapper
Requires-Dist: pyreadline3; platform_system == "Windows"
Requires-Dist: colorama; platform_system == "Windows"
Requires-Dist: cmd2
Requires-Dist: pyyaml
Requires-Dist: rdflib<8,>=7.0.0
Requires-Dist: Pygments
Requires-Dist: xmltodict>=0.13.0
Requires-Dist: typing_extensions
Requires-Dist: iso639-lang
Provides-Extra: dev
Requires-Dist: pytest; extra == "dev"
Requires-Dist: sphinx; extra == "dev"
Requires-Dist: ruff; extra == "dev"
Dynamic: license-file
